iamlistening/__init__.py
iamlistening/config.py
iamlistening/main.py
iamlistening/handler/__init__.py
iamlistening/handler/_client.py
iamlistening/handler/discord.py
iamlistening/handler/guilded.py
iamlistening/handler/lemmy.py
iamlistening/handler/mastodon.py
iamlistening/handler/matrix.py
iamlistening/handler/revolt.py
iamlistening/handler/telegram.py
iamlistening/handler/tradingeconomics.py
iamlistening/handler/twitch.py
iamlistening-6.0.4.dist-info/licenses/LICENSE
iamlistening-6.0.4.dist-info/METADATA
iamlistening-6.0.4.dist-info/WHEEL
iamlistening-6.0.4.dist-info/top_level.txt
iamlistening-6.0.4.dist-info/RECORD
