Metadata-Version: 2.4
Name: iamlistening
Version: 6.0.4
Summary: A python package to interact with messaging platform.
Author-email: mraniki <8766259+mraniki@users.noreply.github.com>
License-Expression: MIT
Project-URL: Homepage, https://github.com/mraniki/iamlistening
Project-URL: Changelog, https://github.com/mraniki/iamlistening/blob/dev/CHANGELOG.rst
Project-URL: Support, https://github.com/mraniki/iamlistening/discussions
Project-URL: Issues, https://github.com/mraniki/iamlistening/issues
Keywords: bot,messaging,discord,telegram,matrix
Classifier: Programming Language :: Python :: 3
Classifier: Programming Language :: Python :: 3.10
Classifier: Programming Language :: Python :: 3.11
Requires-Python: <3.12,>=3.10
License-File: LICENSE
Requires-Dist: dynaconf>=3.1.12
Requires-Dist: loguru>=0.6.0
Requires-Dist: telethon==1.40.0
Requires-Dist: py-cord==2.6.1
Requires-Dist: simplematrixbotlib==2.10.3
Requires-Dist: rocketchat-API==1.35.1
Requires-Dist: Mastodon.py==2.0.1
Requires-Dist: beautifulsoup4==4.13.4
Requires-Dist: guilded.py==1.13.2
Requires-Dist: revolt.py==0.2.0
Requires-Dist: pythorhead==0.33.0; python_version >= "3.10" and python_version < "3.12"
Requires-Dist: twitchio==2.10.0
Requires-Dist: tradingeconomics>=4.3.12
Provides-Extra: dev
Requires-Dist: python-semantic-release>=8.0.8; extra == "dev"
Requires-Dist: ruff~=0.11; extra == "dev"
Requires-Dist: pre-commit~=4.0; extra == "dev"
Provides-Extra: test
Requires-Dist: pytest~=8.0; extra == "test"
Requires-Dist: pytest-cov~=6.0; extra == "test"
Requires-Dist: pytest-asyncio~=0.26; extra == "test"
Requires-Dist: pytest-mock~=3.11; extra == "test"
Requires-Dist: pytest-loguru~=0.4; extra == "test"
Provides-Extra: docs
Requires-Dist: sphinx==7.4.7; extra == "docs"
Requires-Dist: pydata-sphinx-theme~=0.14; extra == "docs"
Requires-Dist: sphinx-hoverxref~=1.3; extra == "docs"
Requires-Dist: sphinx_copybutton==0.5.2; extra == "docs"
Requires-Dist: myst_parser~=4.0; extra == "docs"
Requires-Dist: sphinx_design~=0.6; extra == "docs"
Dynamic: license-file
